linear_regression_tp/__init__.py
linear_regression_tp/linear_regression_tp.py
linear_regression_tp-1.0.1.dist-info/LICENSE.txt
linear_regression_tp-1.0.1.dist-info/METADATA
linear_regression_tp-1.0.1.dist-info/WHEEL
linear_regression_tp-1.0.1.dist-info/top_level.txt
linear_regression_tp-1.0.1.dist-info/RECORD
