Metadata-Version: 2.1
Name: linear-regression-tp
Version: 1.0.1
Summary: An awesome package that does something
Home-page: http://pypi.python.org/pypi/linear_regression_tp/
Author: Mokadem Adel Abdelkader
Author-email: aa.mokadem@esi-sba.dz
License: LICENSE.txt
License-File: LICENSE.txt
Requires-Dist: linear-regression-tp
